febraban_code/__init__.py
febraban_code/febraban_code.py
febraban_code-0.1.1.dist-info/LICENSE
febraban_code-0.1.1.dist-info/METADATA
febraban_code-0.1.1.dist-info/WHEEL
febraban_code-0.1.1.dist-info/RECORD
